{
    "payload": {
        "initializeStatus": 2,
        "questRoomData": {
            "battleNum": 41,
            "questDataId": 299625924,
            "questStageMstId": 4811
        },
        "userData": {
            "characterPoint": 725981,
            "cleaningStatus": 0,
            "cleaningUpdatedTime": 1646246191,
            "comment": "i like kokc",
            "currentCharacterMstId": 194,
            "currentCostumeMstId": 1,
            "currentJobMstId": 8,
            "currentJobRolePosition": 1,
            "currentJobRoleType": 8,
            "currentTotalPower": 302568,
            "currentUserTitleMstId": 906136,
            "deckCost": 382,
            "exp": 0,
            "favoriteAkbMember1": 0,
            "favoriteAkbMember2": 0,
            "favoriteAkbMember3": 0,
            "gameStatus": 10,
            "gvgCharacterMstId": 167,
            "gvgDraw": 0,
            "gvgJobMstId": 2,
            "gvgJobRolePosition": 2,
            "gvgJobRoleType": 2,
            "gvgLose": 142,
            "gvgMaxWinning": 25,
            "gvgTotalPower": 331069,
            "gvgWin": 461,
            "gvgWinning": 1,
            "isGameMaster": 0,
            "lastAccessTime": 1646249734,
            "leaderCardMstId": 0,
            "level": 220,
            "maxCard": 500,
            "maxDeckCardNum": 20,
            "maxDeckNum": 15,
            "maxFriend": 200,
            "maxItem": 100,
            "maxMainLimitBreakSkill": 4,
            "maxNightMare": 500,
            "maxOtherCard": 500,
            "maxProtector": 500,
            "maxStorageCard": 500,
            "maxStorageNightMare": 500,
            "maxStorageOtherCard": 100,
            "maxStorageProtector": 500,
            "maxSubDeckCardNum": 25,
            "maxSubLimitBreakSkill": 0,
            "maxSupportJob": 6,
            "money": 26750595,
            "name": "Kureha",
            "playerId": 486045175,
            "recentLoginTime": "Online",
            "stamina": 344,
            "staminaMax": 220,
            "staminaUpdatedTime": 1646249671,
            "tutorialFinishTime": 1594053759,
            "userId": 822858185
        }
    },
    "status": 200,
    "url": "/api/quest_battle/initialize_stage"
}